logger_mixin/__init__.py
logger_mixin/test_logger_mixin.py
logger_mixin-1.1.0.dist-info/LICENSE
logger_mixin-1.1.0.dist-info/METADATA
logger_mixin-1.1.0.dist-info/WHEEL
logger_mixin-1.1.0.dist-info/top_level.txt
logger_mixin-1.1.0.dist-info/RECORD
